ardoqpy/__init__.py
ardoqpy/ardoqpy.py
ardoqpy/ardoqpy_sync.py
ardoqpy/ardoqpy_v2.py
ardoqpy/test_ardoqpy.py
ardoqpy-0.8.4.data/data/ardoqpy.cfg/ardoqpy.cfg
ardoqpy-0.8.4.dist-info/LICENSE.txt
ardoqpy-0.8.4.dist-info/METADATA
ardoqpy-0.8.4.dist-info/WHEEL
ardoqpy-0.8.4.dist-info/top_level.txt
ardoqpy-0.8.4.dist-info/RECORD
