Metadata-Version: 2.1
Name: ardoqpy
Version: 0.8.4
Summary: A python REST API wrapper for Ardoq - https://ardoq.com.
Home-page: https://github.com/jbaragry/ardoq-python-client
Author: Jason Baragry
Author-email: jason.baragry@gmail.com
License: MIT
Keywords: architecture ardoq REST API wrapper tool
Classifier: Development Status :: 3 - Alpha
Classifier: Intended Audience :: Developers
Classifier: Topic :: Software Development :: Documentation
Classifier: License :: OSI Approved :: MIT License
Classifier: Programming Language :: Python :: 3
Classifier: Programming Language :: Python :: 3.2
Classifier: Programming Language :: Python :: 3.3
Classifier: Programming Language :: Python :: 3.4
Classifier: Programming Language :: Python :: 3.5
Classifier: Programming Language :: Python :: 3.6
Classifier: Programming Language :: Python :: 3.7
Classifier: Programming Language :: Python :: 3.8
Classifier: Programming Language :: Python :: 3.9
Classifier: Programming Language :: Python :: 3.10
License-File: LICENSE.txt
Requires-Dist: cookiejar
Requires-Dist: configparser
Requires-Dist: requests
